blitz_sphinx_theme/__init__.py
blitz_sphinx_theme/breadcrumbs.html
blitz_sphinx_theme/cookie_banner.html
blitz_sphinx_theme/fonts.html
blitz_sphinx_theme/footer.html
blitz_sphinx_theme/header.html
blitz_sphinx_theme/layout.html
blitz_sphinx_theme/search.html
blitz_sphinx_theme/searchbox.html
blitz_sphinx_theme/theme.conf
blitz_sphinx_theme/theme_variables.jinja
blitz_sphinx_theme/versions.html
blitz_sphinx_theme/static/css/theme.css
blitz_sphinx_theme/static/images/arrow-down-orange.svg
blitz_sphinx_theme/static/images/arrow-right-with-tail.svg
blitz_sphinx_theme/static/images/blitz-colab.svg
blitz_sphinx_theme/static/images/blitz-download.svg
blitz_sphinx_theme/static/images/blitz-github.svg
blitz_sphinx_theme/static/images/blitz-jupyterhub.svg
blitz_sphinx_theme/static/images/chevron-down-black.svg
blitz_sphinx_theme/static/images/chevron-down-grey.svg
blitz_sphinx_theme/static/images/chevron-down-orange.svg
blitz_sphinx_theme/static/images/chevron-down-white.svg
blitz_sphinx_theme/static/images/chevron-right-orange.svg
blitz_sphinx_theme/static/images/chevron-right-white.svg
blitz_sphinx_theme/static/images/etched_logo.svg
blitz_sphinx_theme/static/images/etched_logo_icon.svg
blitz_sphinx_theme/static/images/home-footer-background.jpg
blitz_sphinx_theme/static/images/icon-close.svg
blitz_sphinx_theme/static/images/icon-menu-dots-dark.svg
blitz_sphinx_theme/static/images/logo-dark.svg
blitz_sphinx_theme/static/images/logo-facebook-dark.svg
blitz_sphinx_theme/static/images/logo-icon.svg
blitz_sphinx_theme/static/images/logo-twitter-dark.svg
blitz_sphinx_theme/static/images/logo-youtube-dark.svg
blitz_sphinx_theme/static/images/logo.svg
blitz_sphinx_theme/static/images/pytorch-x.svg
blitz_sphinx_theme/static/images/search-icon-black.svg
blitz_sphinx_theme/static/images/search-icon.svg
blitz_sphinx_theme/static/images/view-page-source-icon.svg
blitz_sphinx_theme/static/js/modernizr.min.js
blitz_sphinx_theme/static/js/theme.js
blitz_sphinx_theme-0.1.19.dist-info/LICENSE
blitz_sphinx_theme-0.1.19.dist-info/METADATA
blitz_sphinx_theme-0.1.19.dist-info/WHEEL
blitz_sphinx_theme-0.1.19.dist-info/entry_points.txt
blitz_sphinx_theme-0.1.19.dist-info/top_level.txt
blitz_sphinx_theme-0.1.19.dist-info/RECORD
