Metadata-Version: 2.1
Name: blitz_sphinx_theme
Version: 0.1.19
Summary: Blitz Sphinx Theme
Home-page: https://github.com/etched-ai/blitz_sphinx_theme
Author: Etched
Author-email: colin_x@etched.com
License: MIT License
Classifier: Development Status :: 5 - Production/Stable
Classifier: Environment :: Web Environment
Classifier: Intended Audience :: Developers
Classifier: Intended Audience :: System Administrators
Classifier: License :: OSI Approved :: MIT License
Classifier: Operating System :: OS Independent
Classifier: Programming Language :: Python
Classifier: Topic :: Internet
Classifier: Topic :: Software Development :: Documentation
License-File: LICENSE
Requires-Dist: sphinx ==6.0.0
Requires-Dist: myst-nb ==1.1.0
